fifo.v
`timescale 1ns/1ps

module fifo (
    input clk,
    input reset,
    input wr_en,
    input rd_en,
    input [7:0] data_in,
    output reg [7:0] data_out,
    output full,
    output empty
);

    reg [7:0] mem [0:7];   // 8-depth FIFO
    reg [2:0] wr_ptr;      // write pointer
    reg [2:0] rd_ptr;      // read pointer
    reg [3:0] count;       // number of elements

    assign full  = (count == 8);
    assign empty = (count == 0);

    always @(posedge clk or posedge reset) begin
        if (reset) begin
            wr_ptr   <= 0;
            rd_ptr   <= 0;
            count    <= 0;
            data_out <= 0;
        end else begin
            // Write
            if (wr_en && !full) begin
                mem[wr_ptr] <= data_in;
                wr_ptr <= wr_ptr + 1;
                count  <= count + 1;
            end
            // Read
            if (rd_en && !empty) begin
                data_out <= mem[rd_ptr];
                rd_ptr <= rd_ptr + 1;
                count  <= count - 1;
            end
        end
    end

endmodule

fifo_tb.v
`timescale 1ns/1ps

module fifo_tb;

reg clk;
reg reset;
reg wr_en;
reg rd_en;
reg [7:0] data_in;
wire [7:0] data_out;
wire full;
wire empty;

// Instantiate FIFO
fifo uut (
    .clk(clk),
    .reset(reset),
    .wr_en(wr_en),
    .rd_en(rd_en),
    .data_in(data_in),
    .data_out(data_out),
    .full(full),
    .empty(empty)
);

// ✅ Add this clock generator here
always #5 clk = ~clk;  // toggles every 5 ns

// ✅ Add reset and stimulus here
initial begin
    clk = 0;
    reset = 1;
    wr_en = 0;
    rd_en = 0;
    data_in = 0;

    #10 reset = 0;  // release reset after 10 ns

    // Write data
    #10 wr_en = 1; data_in = 8'd10;
    #10 data_in = 8'd20;
    #10 data_in = 8'd30;
    #10 wr_en = 0;

    // Read data
    #10 rd_en = 1;
    #30 rd_en = 0;

    #200 $finish;
end

// ✅ Add waveform dump here
initial begin
    $dumpfile("waveform.vcd");
    $dumpvars(0, fifo_tb);
end

endmodule

waveform.vcd
$date
	Thu May 21 13:48:33 2026
$end
$version
	Icarus Verilog
$end
$timescale
	1ps
$end
$scope module fifo_tb $end
$var wire 1 ! full $end
$var wire 1 " empty $end
$var wire 8 # data_out [7:0] $end
$var reg 1 $ clk $end
$var reg 8 % data_in [7:0] $end
$var reg 1 & rd_en $end
$var reg 1 ' reset $end
$var reg 1 ( wr_en $end
$scope module uut $end
$var wire 1 $ clk $end
$var wire 8 ) data_in [7:0] $end
$var wire 1 & rd_en $end
$var wire 1 ' reset $end
$var wire 1 ( wr_en $end
$var wire 1 ! full $end
$var wire 1 " empty $end
$var reg 4 * count [3:0] $end
$var reg 8 + data_out [7:0] $end
$var reg 3 , rd_ptr [2:0] $end
$var reg 3 - wr_ptr [2:0] $end
$upscope $end
$upscope $end
$enddefinitions $end
#0
$dumpvars
b0 -
b0 ,
b0 +
b0 *
b0 )
0(
1'
0&
b0 %
0$
b0 #
1"
0!
$end
#5000
1$
#10000
0$
0'
#15000
1$
#20000
0$
b1010 %
b1010 )
1(
#25000
0"
b1 *
b1 -
1$
#30000
0$
b10100 %
b10100 )
#35000
b10 *
b10 -
1$
#40000
0$
b11110 %
b11110 )
#45000
b11 *
b11 -
1$
#50000
0$
0(
#55000
1$
#60000
0$
1&
#65000
b10 *
b1 ,
b1010 #
b1010 +
1$
#70000
0$
#75000
b1 *
b10 ,
b10100 #
b10100 +
1$
#80000
0$
#85000
1"
b0 *
b11 ,
b11110 #
b11110 +
1$
#90000
0$
0&
